gith/__init__.py
gith/cli.py
gith/console.py
gith/helpers.py
gith/messages.py
gith-0.2.4.dist-info/LICENSE
gith-0.2.4.dist-info/METADATA
gith-0.2.4.dist-info/WHEEL
gith-0.2.4.dist-info/entry_points.txt
gith-0.2.4.dist-info/top_level.txt
gith-0.2.4.dist-info/RECORD
