Metadata-Version: 2.2
Name: gith
Version: 0.2.4
Summary: A Typer-based helper for Git operations
Author-email: "Reinaldo J. Menéndez" <rejamen@gmail.com>
License: MIT License
Project-URL: Repository, https://github.com/rejamen/gith
Project-URL: Issues, https://github.com/rejamen/gith/issues
Classifier: Programming Language :: Python :: 3
Classifier: Programming Language :: Python :: 3.7
Classifier: Programming Language :: Python :: 3.8
Classifier: Programming Language :: Python :: 3.9
Classifier: Programming Language :: Python :: 3.10
Classifier: Programming Language :: Python :: 3.11
Classifier: Programming Language :: Python :: 3.12
Classifier: License :: OSI Approved :: MIT License
Classifier: Operating System :: OS Independent
Requires-Python: >=3.7
License-File: LICENSE
Requires-Dist: typer>=0.15.1
Requires-Dist: rich>=10.11.0
Requires-Dist: pyyaml>=5.4
